saltext/sap_nwabap/__init__.py
saltext/sap_nwabap/loader.py
saltext/sap_nwabap/version.py
saltext/sap_nwabap/_modules/sap_nwabap.py
saltext/sap_nwabap/_states/sap_nwabap.py
saltext/sap_nwabap/modules/sap_nwabap.py
saltext/sap_nwabap/states/sap_nwabap.py
saltext.sap_nwabap-1.0.1.dist-info/LICENSE
saltext.sap_nwabap-1.0.1.dist-info/METADATA
saltext.sap_nwabap-1.0.1.dist-info/WHEEL
saltext.sap_nwabap-1.0.1.dist-info/entry_points.txt
saltext.sap_nwabap-1.0.1.dist-info/top_level.txt
saltext.sap_nwabap-1.0.1.dist-info/RECORD
